kestrel_interface_opensearch/__init__.py
kestrel_interface_opensearch/config.py
kestrel_interface_opensearch/interface.py
kestrel_interface_opensearch/ossql.py
kestrel_interface_opensearch-2.0.0b0.dist-info/METADATA
kestrel_interface_opensearch-2.0.0b0.dist-info/WHEEL
kestrel_interface_opensearch-2.0.0b0.dist-info/top_level.txt
kestrel_interface_opensearch-2.0.0b0.dist-info/RECORD
