Metadata-Version: 2.1
Name: kestrel_interface_opensearch
Version: 2.0.0b0
Summary: Kestrel OpenSearch Datasource Interface
Maintainer-email: Xiaokui Shu <xiaokui.shu@ibm.com>, Paul Coccoli <pcoccoli@us.ibm.com>
License: Apache 2.0 License
Project-URL: Homepage, https://github.com/opencybersecurityalliance/kestrel-lang
Project-URL: Documentation, https://kestrel.readthedocs.io/
Project-URL: Repository, https://github.com/opencybersecurityalliance/kestrel-lang.git
Keywords: kestrel,cybersecurity,threat hunting
Classifier: Topic :: Security
Classifier: Operating System :: OS Independent
Classifier: Development Status :: 4 - Beta
Classifier: Programming Language :: Python :: 3
Requires-Python: >=3.8
Requires-Dist: kestrel-core >=2.0.0b
Requires-Dist: opensearch-py >=2.6.0
